notebookquery/__init__.py
notebookquery/css/custom.css
notebookquery/rendering.py
notebookquery/sqlext.py
notebookquery-0.1.1.dist-info/LICENSE
notebookquery-0.1.1.dist-info/WHEEL
notebookquery-0.1.1.dist-info/METADATA
notebookquery-0.1.1.dist-info/RECORD
