Metadata-Version: 2.1
Name: notebookquery
Version: 0.1.1
Summary: SQL integration and table display for ipython notebooks
Author: Robert Lechte
Author-email: robert.lechte@dpc.vic.gov.au
Requires-Python: >=3.8
Classifier: Programming Language :: Python :: 3
Classifier: Programming Language :: Python :: 3.8
Requires-Dist: nouns
Requires-Dist: results
